trust3_common/VERSION
trust3_common/__init__.py
trust3_common/async_base_rest_http_client.py
trust3_common/async_http_transport.py
trust3_common/audit_spooler.py
trust3_common/config_utils.py
trust3_common/constants.py
trust3_common/encryption.py
trust3_common/file_utils.py
trust3_common/http_transport.py
trust3_common/lru_cache.py
trust3_common/paig_exception.py
trust3_common/rbac_manager.py
trust3_common/response.py
trust3_common-1.0.0.dist-info/METADATA
trust3_common-1.0.0.dist-info/WHEEL
trust3_common-1.0.0.dist-info/RECORD
