Metadata-Version: 2.4
Name: trust3-common
Version: 1.0.0
Summary: Common utilities and components for building secure AI governance applications
Project-URL: Documentation, https://docs.trust3.ai
Author-email: Trust3 Team <support@trust3.ai>
License:                                  Apache License
Classifier: License :: Other/Proprietary License
Classifier: Operating System :: OS Independent
Classifier: Programming Language :: Python :: 3
Requires-Python: >=3.8.1
Requires-Dist: cryptography==41.0.4
Requires-Dist: jproperties>=2.1.1
Requires-Dist: urllib3>=2.0.6
